customer_segmentation_toolkit/__init__.py
customer_segmentation_toolkit/_nbdev.py
customer_segmentation_toolkit/analyse_customers.py
customer_segmentation_toolkit/analyse_purchases.py
customer_segmentation_toolkit/clean_rows.py
customer_segmentation_toolkit/data_zoo.py
customer_segmentation_toolkit/load_split.py
customer_segmentation_toolkit/data/__init__.py
customer_segmentation_toolkit/data/analyse_customers.py
customer_segmentation_toolkit/data/analyse_purchases.py
customer_segmentation_toolkit/data/clean_rows.py
customer_segmentation_toolkit/data/load_split.py
customer_segmentation_toolkit-0.1.1.dist-info/LICENSE
customer_segmentation_toolkit-0.1.1.dist-info/METADATA
customer_segmentation_toolkit-0.1.1.dist-info/WHEEL
customer_segmentation_toolkit-0.1.1.dist-info/entry_points.txt
customer_segmentation_toolkit-0.1.1.dist-info/top_level.txt
customer_segmentation_toolkit-0.1.1.dist-info/RECORD
