Metadata-Version: 2.1
Name: customer-segmentation-toolkit
Version: 0.1.1
Summary: Data transformations for the Engineering Lab2 Feature-Store-for-ML
Home-page: https://github.com/artemlops/customer-segmentation-toolkit/tree/master/
Author: featurologists-team
Author-email: ajuszkowski@gmail.com
License: Apache Software License 2.0
Keywords: MLOps ML feature_store data_engineering
Platform: UNKNOWN
Classifier: Development Status :: 3 - Alpha
Classifier: Intended Audience :: Developers
Classifier: Natural Language :: English
Classifier: Programming Language :: Python :: 3.6
Classifier: Programming Language :: Python :: 3.7
Classifier: Programming Language :: Python :: 3.8
Classifier: License :: OSI Approved :: Apache Software License
Requires-Python: >=3.6
Requires-Dist: pip
Requires-Dist: packaging
Requires-Dist: pandas (>=1.0.0)
Requires-Dist: nltk (>=3.6.2)
Requires-Dist: matplotlib (>=3.3.4)
Requires-Dist: scikit-learn (>=0.24.2)
Requires-Dist: numpy (>=1.19)
Requires-Dist: seaborn (>=0.11.1)
Provides-Extra: dev
